RiScKy C0RE/src/RV32_Controller.v
/*/////////////////////////////////////////////
 File: RV32_Controller.v
 Author: Manav Shah
 ----------------------------------------------

    ██████╗ ██╗███████╗ ██████╗██╗  ██╗██╗   ██╗
    ██╔══██╗██║██╔════╝██╔════╝██║ ██╔╝╚██╗ ██╔╝
    ██████╔╝██║███████╗██║     █████╔╝  ╚████╔╝ 
    ██╔══██╗██║╚════██║██║     ██╔═██╗   ╚██╔╝  
    ██║  ██║██║███████║╚██████╗██║  ██╗   ██║   
    ╚═╝  ╚═╝╚═╝╚══════╝ ╚═════╝╚═╝  ╚═╝   ╚═╝   
 ----------------------------------------------
                                    
 Copyright (c) 2024 MANAV SHAH
*//////////////////////////////////////////////

module RV32_Controller(i_instuction, BrEq, BrLt,
PCSel, ImmSel, BrUn, ASel, BSel, ALUSel, MemRW, RegWEn, WBSel);

input [31:0] i_instuction;
input BrEq,BrLt;

// wire reduced instruction.
wire [10:0]red_inst;
assign red_inst = {i_instuction[30],i_instuction[14:12],i_instuction[6:2],BrEq,BrLt};

// all control signals.
output PCSel;
output [2:0]ImmSel;
output BrUn;
output ASel,BSel;
output [3:0]ALUSel;
output MemRW;
output RegWEn;
output [1:0]WBSel;

wire [14:0]control_word;
assign control_word = (red_inst[10:2] == 9'b000001100) ? 15'b000000000000101 :  // add
                      (red_inst[10:2] == 9'b100001100) ? 15'b000000000010101 :  // sub
                      (red_inst[9:2]  ==  8'b00101100) ? 15'b000000000100101 :  // sll
                      (red_inst[9:2]  ==  8'b01001100) ? 15'b000000000110101 :  // slt
                      (red_inst[9:2]  ==  8'b01101100) ? 15'b000000001000101 :  // sltu
                      (red_inst[9:2]  ==  8'b10001100) ? 15'b000000001010101 :  // xor
                      (red_inst[10:2] == 9'b010101100) ? 15'b000000001100101 :  // srl
                      (red_inst[10:2] == 9'b110101100) ? 15'b000000001110101 :  // sra
                      (red_inst[9:2]  ==  8'b11001100) ? 15'b000000010000101 :  // or                  
                      (red_inst[9:2]  ==  8'b11101100) ? 15'b000000010010101 :  // and

                      (red_inst[9:2]  ==  8'b00000100) ? 15'b000100100000101 :  // addi
                      (red_inst[9:2]  ==  8'b01000100) ? 15'b000100100110101 :  // slti
                      (red_inst[9:2]  ==  8'b01100100) ? 15'b000100101000101 :  // sltiu
                      (red_inst[9:2]  ==  8'b10000100) ? 15'b000100101010101 :  // xori
                      (red_inst[9:2]  ==  8'b11000100) ? 15'b000100110000101 :  // ori
                      (red_inst[9:2]  ==  8'b11100100) ? 15'b000100110010101 :  // andi
                      (red_inst[9:2]  ==  8'b00100100) ? 15'b000100100100101 :  // slli
                      (red_inst[10:2]==  9'b010100100) ? 15'b000100101100101 :  // srli
                      (red_inst[10:2]==  9'b110100100) ? 15'b000100101110101 :  // srai

                      (red_inst[9:2]  ==  8'b00000000) ? 15'b000100110100101 :  // lb
                      (red_inst[9:2]  ==  8'b00100000) ? 15'b000100110110101 :  // lh
                      (red_inst[9:2]  ==  8'b01000000) ? 15'b000100100000101 :  // lw
                      (red_inst[9:2]  ==  8'b10000000) ? 15'b000100111000101 :  // lbu
                      (red_inst[9:2]  ==  8'b10100000) ? 15'b000100111010101 :  // lhu

                      (red_inst[9:2]  ==  8'b00001000) ? 15'b001000110100101 :  // sb
                      (red_inst[9:2]  ==  8'b00101000) ? 15'b001000110110101 :  // sh
                      (red_inst[9:2]  ==  8'b01001000) ? 15'b001000100000101 :  // sw

                      (red_inst[9:1]  == 9'b000110000) ? 15'b001101100000000 :  // beq BrEq = 0
                      (red_inst[9:1]  == 9'b000110001) ? 15'b101101100000000 :  // beq BrEq = 1
                      (red_inst[9:1]  == 9'b001110000) ? 15'b101101100000000 :  // bne BrEq = 0
                      (red_inst[9:1]  == 9'b001110001) ? 15'b001101100000000 :  // bne BrEq = 1

                      ({red_inst[9:2],red_inst[0]} == 9'b100110001) ? 15'b101101100000000 : // blt BLT = 1
                      ({red_inst[9:2],red_inst[0]} == 9'b110110001) ? 15'b101111100000000 : // bltu BLT = 1

                      ({red_inst[9:2],red_inst[0]} == 9'b101110000) ? 15'b101101100000000 : // bge brEq = (0,1) brLT = (0)

                      ({red_inst[6:2]} == 5'b11011) ? 15'b110001100000110 : // jal 
                      ({red_inst[6:2]} == 5'b11001) ? 15'b100100100000110 : // jalr 

                      ({red_inst[6:2]} == 5'b01101) ? 15'b010100111100101 : // lui // made different alu control '1110' which forwards B to output and // new immediate type named 'U' '101'

                      15'b000000000000101;

assign PCSel = control_word[14];
assign ImmSel = control_word[13:11];
assign BrUn = control_word[10];
assign ASel = control_word[9];
assign BSel = control_word[8];
assign ALUSel = control_word[7:4];
assign MemRW = control_word[3];
assign RegWEn = control_word[2];
assign WBSel = control_word[1:0];

endmodule

// for instruction encoding, 9 bits of the full 32bit instruction will be used.
// bit 30, [14:12] , [6,2].
// BrEq and BrLt will also be used.
// so in total, 11 bits will be used to generate control word output. 15 bits
// control word is 15 bits 


/*
                      (red_inst[9:1]  == 9'b000110000) ? 15'b001101100000000 :  // beq BrEq = 0
                      (red_inst[9:1]  == 9'b000110001) ? 15'b101101100000000 :  // beq BrEq = 1
                      (red_inst[9:1]  == 9'b001110000) ? 15'b101101100000000 :  // bne BrEq = 0
                      (red_inst[9:1]  == 9'b001110001) ? 15'b001101100000000 :  // bne BrEq = 1

*/

src/mux.v
/*/////////////////////////////////////////////
 File: mux.v
 Author: Manav Shah
 ----------------------------------------------

    ██████╗ ██╗███████╗ ██████╗██╗  ██╗██╗   ██╗
    ██╔══██╗██║██╔════╝██╔════╝██║ ██╔╝╚██╗ ██╔╝
    ██████╔╝██║███████╗██║     █████╔╝  ╚████╔╝ 
    ██╔══██╗██║╚════██║██║     ██╔═██╗   ╚██╔╝  
    ██║  ██║██║███████║╚██████╗██║  ██╗   ██║   
    ╚═╝  ╚═╝╚═╝╚══════╝ ╚═════╝╚═╝  ╚═╝   ╚═╝   
 ----------------------------------------------
                                    
 Copyright (c) 2024 MANAV SHAH
*//////////////////////////////////////////////

module mux(a,b,c,sel);

input [31:0]a,b;
input sel;

output [31:0]c;

assign c = (sel == 1'b1) ? b : a;

endmodule

module mux3(a,b,c,d,sel);

input [31:0]a,b,c;
input [1:0]sel;

output [31:0]d;

assign d = (sel == 2'b00) ? a : (sel == 2'b01) ? b : (sel == 2'b10) ? c : 32'h00000000;

endmodule

single_cycle_rv32i/Data_mem.v
module Data_mem(clk,A_mem,DataIP,MemRW,D_read); //single read write port 
input clk;
input MemRW; //active high
input [31:0] A_mem;  // address to which input data is stored.
input [31:0] DataIP; // Input Data

output [31:0] D_read;  // the data from memory is given as output

reg [31:0] D_mem [1023:0];  // this is the actual memory

initial begin
    $readmemh("/memory/D_mem.hex",D_mem);
end

//MemRW = 0 : read , MemRW = 1 : write

always @(posedge clk)begin
if(MemRW == 1'b1)begin
   D_mem[A_mem] <= DataIP;
end
end

assign D_read = (MemRW == 1'b0) ? D_mem[A_mem] : 32'h00000000;

endmodule

RiScKy C0RE/src/branch_comp.v
/*/////////////////////////////////////////////
 File: branch_comp.v
 Author: Manav Shah
 ----------------------------------------------

    ██████╗ ██╗███████╗ ██████╗██╗  ██╗██╗   ██╗
    ██╔══██╗██║██╔════╝██╔════╝██║ ██╔╝╚██╗ ██╔╝
    ██████╔╝██║███████╗██║     █████╔╝  ╚████╔╝ 
    ██╔══██╗██║╚════██║██║     ██╔═██╗   ╚██╔╝  
    ██║  ██║██║███████║╚██████╗██║  ██╗   ██║   
    ╚═╝  ╚═╝╚═╝╚══════╝ ╚═════╝╚═╝  ╚═╝   ╚═╝   
 ----------------------------------------------
                                    
 Copyright (c) 2024 MANAV SHAH
*//////////////////////////////////////////////

module branch_comp(A,B,BrUn,BrEq,BrLt);

input [31:0]A,B;
input BrUn;

output BrEq,BrLt;

assign BrEq = ((BrUn == 1'b0) & (A == B)) ? 1 :
              ((BrUn == 1'b1) & (A[30:0] == B[30:0])) ? 1 : 0;
 
assign BrLt = ((BrUn == 1'b0) & (A < B)) ? 1 :
              ((BrUn == 1'b1) & (A[30:0] < B[30:0])) ? 1 : 0; 

endmodule

RiScKy C0RE/src/Imm_Gen.v
/*/////////////////////////////////////////////
 File: Imm_Gen.v
 Author: Manav Shah
 ----------------------------------------------

    ██████╗ ██╗███████╗ ██████╗██╗  ██╗██╗   ██╗
    ██╔══██╗██║██╔════╝██╔════╝██║ ██╔╝╚██╗ ██╔╝
    ██████╔╝██║███████╗██║     █████╔╝  ╚████╔╝ 
    ██╔══██╗██║╚════██║██║     ██╔═██╗   ╚██╔╝  
    ██║  ██║██║███████║╚██████╗██║  ██╗   ██║   
    ╚═╝  ╚═╝╚═╝╚══════╝ ╚═════╝╚═╝  ╚═╝   ╚═╝   
 ----------------------------------------------
                                    
 Copyright (c) 2024 MANAV SHAH
*//////////////////////////////////////////////

module Imm_Gen(Instr,ImmSel,immediate);

input [31:0]Instr;
input [2:0]ImmSel;

output [31:0]immediate;

/* 
ImmSel
0       nothing
1       I type
2       S type 
3       B type 
4       J type
*/

assign immediate = (ImmSel == 3'b001 & Instr[31] == 1'b0) ? {{20{1'b0}},Instr[31:20]} :  // I type immediate 
                   (ImmSel == 3'b001 & Instr[31] == 1'b1) ? {{20{1'b1}},Instr[31:20]} :  // consider sign extension of most signifiacnt bit ie. bit 31 here
                   (ImmSel == 3'b010 & Instr[31] == 1'b0) ? {{20{1'b0}},Instr[31:25],Instr[11:7]} : // S type immediate 
                   (ImmSel == 3'b010 & Instr[31] == 1'b1) ? {{20{1'b1}},Instr[31:25],Instr[11:7]} : 
                   (ImmSel == 3'b011 & Instr[31] == 1'b0) ? {{19{1'b0}},Instr[31],Instr[7],Instr[30:25],Instr[11:8],1'b0} : // B type immediate 
                   (ImmSel == 3'b011 & Instr[31] == 1'b1) ? {{19{1'b1}},Instr[31],Instr[7],Instr[30:25],Instr[11:8],1'b0} : 
                   (ImmSel == 3'b100 & Instr[31] == 1'b0) ? {{11{1'b0}},Instr[31],Instr[19:12],Instr[20],Instr[30:21],1'b0} :     // has to be sign extended
                   (ImmSel == 3'b100 & Instr[31] == 1'b1) ? {{11{1'b1}},Instr[31],Instr[19:12],Instr[20],Instr[30:21],1'b0} :     // has to be sign extended
                   32'h00000000;

endmodule

RiScKy C0RE/src/ALU.v
/*/////////////////////////////////////////////
 File: ALU.v
 Author: Manav Shah
 ----------------------------------------------

    ██████╗ ██╗███████╗ ██████╗██╗  ██╗██╗   ██╗
    ██╔══██╗██║██╔════╝██╔════╝██║ ██╔╝╚██╗ ██╔╝
    ██████╔╝██║███████╗██║     █████╔╝  ╚████╔╝ 
    ██╔══██╗██║╚════██║██║     ██╔═██╗   ╚██╔╝  
    ██║  ██║██║███████║╚██████╗██║  ██╗   ██║   
    ╚═╝  ╚═╝╚═╝╚══════╝ ╚═════╝╚═╝  ╚═╝   ╚═╝   
 ----------------------------------------------
                                    
 Copyright (c) 2024 MANAV SHAH
*//////////////////////////////////////////////

module ALU(A,B,control,ALU_result);

input [31:0] A,B;
//input control;
// control will have to be 3 bits wide now to support all R type instuctions. and alu will also have to be more functional.
input [3:0]control;

output [31:0]ALU_result;

//wires
wire [31:0]alu_slt;

assign alu_slt = (A < B) ? 32'h00000001: 32'h00000000;
//assign ALU_result = (control == 1'b0) ? (A + B) : ( A - B);
assign ALU_result = (control == 4'b0000) ? A + B :        //0 add
                    (control == 4'b0001) ? A - B :        //1 sub
                    (control == 4'b0010) ? A << B[4:0] :  //2 sll
                    (control == 4'b0011) ? alu_slt :      //3 slt   set less than signed  :writing 1 to rd if rs1 < rs2, 0 otherwise
                    (control == 4'b0100) ? alu_slt :      //4 sltu  set less than unsigned
                    (control == 4'b0101) ? A ^ B :        //5 xor
                    (control == 4'b0110) ? A >> B[4:0] :  // srl
                    (control == 4'b0111) ? A >>> B[4:0] : // sra
                    (control == 4'b1000) ? A | B :        // or
                    (control == 4'b1001) ? A & B :        // and
                    
                    //Loads and stores
                    (control == 4'b1010) ? ({{24{1'b0}},A[7:0]} +  B)  : // LB load only 8 bits
                    (control == 4'b1011) ? ({{16{1'b0}},A[15:0]} + B)  : // LH     
                    (control == 4'b1100) ? ({{25{1'b0}},A[6:0]} +  B)  : // LBU  
                    (control == 4'b1101) ? ({{17{1'b0}},A[14:0]} + B)  : // LHU            

                    //default 
                    32'h00000000;
                    
// SLL, SRL, and SRA perform logical left, logical right, and arithmetic right shifts on the value in 
// register rs1 by the shift amount held in the lower 5 bits of register rs2

endmodule

RV32I_datapath/Regfile.v
/*/////////////////////////////////////////////
 File: Regfile.v
 Author: Manav Shah
 ----------------------------------------------

    ██████╗ ██╗███████╗ ██████╗██╗  ██╗██╗   ██╗
    ██╔══██╗██║██╔════╝██╔════╝██║ ██╔╝╚██╗ ██╔╝
    ██████╔╝██║███████╗██║     █████╔╝  ╚████╔╝ 
    ██╔══██╗██║╚════██║██║     ██╔═██╗   ╚██╔╝  
    ██║  ██║██║███████║╚██████╗██║  ██╗   ██║   
    ╚═╝  ╚═╝╚═╝╚══════╝ ╚═════╝╚═╝  ╚═╝   ╚═╝   
 ----------------------------------------------
                                    
 Copyright (c) 2024 MANAV SHAH
*//////////////////////////////////////////////

module Regfile(clk,rst,WE,AddD,DataD,AddA,DataA,AddB,DataB);
input clk,rst,WE;
input [4:0] AddA,AddB,AddD;
input [31:0] DataD;
/*
rst: is reset signal(active low).
WE: is Write Enable signal.
AddA,AddB : registers are read at these addresses
and read values are given out at DataA and DataB respectively.
AddD : is the address for the register which is to be written with DataD.
*/
output [31:0] DataA,DataB;

reg [31:0] xreg [31:0]; //x0 to x31 : RV32 registers
reg [4:0]index = 1;

initial begin
    $readmemh("reg_load.hex",xreg,0,31); // custom program to load registers from gui
end

always @(posedge clk)begin
   if(WE &(AddD != 5'h00))
       xreg[AddD] <= DataD;  
end

assign DataA = (rst == 1'b0) ? 32'h00000000 : xreg[AddA];
assign DataB = (rst == 1'b0) ? 32'h00000000 : xreg[AddB];

endmodule

single_cycle_rv32i/Instruction_Memory.v
module Instruction_memory(rst,A,RD);

input rst;
input [31:0]A;

output [31:0]RD;

reg [31:0]mem[1023:0];

initial begin
    $readmemh("instructions.hex",mem);
end

assign RD = (rst == 1'b0) ? {32{1'b0}} : mem[A];


endmodule

RiScKy C0RE/src/PC_adder.v
/*/////////////////////////////////////////////
 File: PC_adder.v
 Author: Manav Shah
 ----------------------------------------------

    ██████╗ ██╗███████╗ ██████╗██╗  ██╗██╗   ██╗
    ██╔══██╗██║██╔════╝██╔════╝██║ ██╔╝╚██╗ ██╔╝
    ██████╔╝██║███████╗██║     █████╔╝  ╚████╔╝ 
    ██╔══██╗██║╚════██║██║     ██╔═██╗   ╚██╔╝  
    ██║  ██║██║███████║╚██████╗██║  ██╗   ██║   
    ╚═╝  ╚═╝╚═╝╚══════╝ ╚═════╝╚═╝  ╚═╝   ╚═╝   
 ----------------------------------------------
                                    
 Copyright (c) 2024 MANAV SHAH
*//////////////////////////////////////////////

module PC_adder(PC_add,PCP4_add);

input [31:0]PC_add;

output [31:0]PCP4_add;

assign PCP4_add = PC_add + 32'd4;

endmodule

RV32I_datapath/PC.v
module PC(clk,rst,PC,PCP4);

input clk,rst;
input [31:0]PCP4;
output reg [31:0]PC;

always @(posedge clk)begin

    if(rst == 1'b0)begin
        //if reset is active, PC = 0;
        PC <= {32{1'b0}};
    end
    else begin
        PC <= PCP4;
    end

end

endmodule

RV32I_datapath/RV32I.v
`include "PC.v"
`include "PC_adder.v"
`include "mux.v"
`include "Regfile.v"
`include "Instruction_Memory.v"
`include "ALU.v"
`include "Imm_Gen.v"
`include "branch_comp.v"
`include "Data_mem.v"
`include "RV32_Controller.v"

module RV32I(clk,rst);

input clk,rst;

//wires
wire [31:0]PC_out;
wire [31:0]PC_in;

wire [31:0]PC_4;

wire [31:0]alu;

wire [31:0]reg_DataA;
wire [31:0]reg_DataB;

wire [31:0]immediate;

wire [31:0]alu_in1;
wire [31:0]alu_in2;


wire [31:0]DataR; // Data memory output

wire [31:0]wb;

// Instruction
wire [31:0]Instr;

// control signal wires
wire PCSel;
wire RegWEn;
wire ASel;
wire BSel;
wire [3:0]ALUSel;
wire [2:0]ImmSel;
wire BrUn;
wire MemRW;
wire [1:0]WBSel;

wire BrEq,BrLt;

mux muxPC(.a(PC_4),
          .b(alu),
          .c(PC_in),
          .sel(PCSel));

PC PC_Top(.clk(clk),
          .rst(rst),
          .PC(PC_out),
          .PCP4(PC_in));

PC_adder PCPlus4Top(.PC_add(PC_out),
                    .PCP4_add(PC_4));

Instruction_memory imem(.rst(rst),
                   .A(PC_out),
                   .RD(Instr));

Regfile regfile(.clk(clk),
        .rst(rst),
        .WE(RegWEn),
        .AddD(Instr[11:7]),
        .DataD(wb),
        .AddA(Instr[19:15]),
        .DataA(reg_DataA),
        .AddB(Instr[24:20]),
        .DataB(reg_DataB));

mux muxA(.a(reg_DataA),
         .b(PC_out),
         .c(alu_in1),
         .sel(ASel));

mux muxB(.a(reg_DataB),
         .b(immediate),
         .c(alu_in2),
         .sel(BSel));

ALU ALU_Top(.A(alu_in1),
            .B(alu_in2),
            .control(ALUSel),
            .ALU_result(alu));

Imm_Gen Imm_Gen(.Instr(Instr),
                .ImmSel(ImmSel),
                .immediate(immediate));

branch_comp branch_comp(.A(reg_DataA),
                        .B(reg_DataB),
                        .BrUn(BrUn),
                        .BrEq(BrEq),
                        .BrLt(BrLt));

Data_mem Data_mem(.clk(clk),
                  .A_mem(alu),
                  .DataIP(reg_DataB),
                  .MemRW(MemRW),
                  .D_read(DataR)); 

mux3 mux3(.a(DataR),
          .b(alu),
          .c(PC_4),
          .d(wb),
          .sel(WBSel));

RV32_Controller Controller(.i_instuction(Instr), 
                           .BrEq(BrEq), 
                           .BrLt(BrLt),
                           .PCSel(PCSel), 
                           .ImmSel(ImmSel), 
                           .BrUn(BrUn), 
                           .ASel(ASel), 
                           .BSel(BSel), 
                           .ALUSel(ALUSel), 
                           .MemRW(MemRW), 
                           .RegWEn(RegWEn), 
                           .WBSel(WBSel));

endmodule

RiScKy C0RE/RV32_tb.v
/*/////////////////////////////////////////////
 File: RV32_tb.v
 Author: Manav Shah
 ----------------------------------------------

    ██████╗ ██╗███████╗ ██████╗██╗  ██╗██╗   ██╗
    ██╔══██╗██║██╔════╝██╔════╝██║ ██╔╝╚██╗ ██╔╝
    ██████╔╝██║███████╗██║     █████╔╝  ╚████╔╝ 
    ██╔══██╗██║╚════██║██║     ██╔═██╗   ╚██╔╝  
    ██║  ██║██║███████║╚██████╗██║  ██╗   ██║   
    ╚═╝  ╚═╝╚═╝╚══════╝ ╚═════╝╚═╝  ╚═╝   ╚═╝   
 ----------------------------------------------
                                    
 Copyright (c) 2024 MANAV SHAH
*//////////////////////////////////////////////

`include "RV32I.v"

module RV32_tb();

reg clk=0,rst;

//module instantiation
RV32I DUT(.clk(clk),
             .rst(rst));

// clocking
always begin
    clk = ~clk;
    #50;
end

initial begin
    $dumpfile("RV32_tb.vcd");
    $dumpvars(0,RV32_tb);
end

initial begin

    // give a reset signal (active low)
    rst = 1'b0;
    #150;

    rst = 1'b1;
    #3000;
    $display("End Of Test");
    $finish;
end
endmodule

RiScKy C0RE/src/RV32_tb.vcd
$date
	Fri Jul 05 19:19:23 2024
$end
$version
	Icarus Verilog
$end
$timescale
	1s
$end
$scope module RV32_tb $end
$var reg 1 ! clk $end
$var reg 1 " rst $end
$scope module DUT $end
$var wire 1 ! clk $end
$var wire 1 " rst $end
$var wire 32 # wb [31:0] $end
$var wire 32 $ reg_DataB [31:0] $end
$var wire 32 % reg_DataA [31:0] $end
$var wire 32 & immediate [31:0] $end
$var wire 32 ' alu_in2 [31:0] $end
$var wire 32 ( alu_in1 [31:0] $end
$var wire 32 ) alu [31:0] $end
$var wire 2 * WBSel [1:0] $end
$var wire 1 + RegWEn $end
$var wire 32 , PC_out [31:0] $end
$var wire 32 - PC_in [31:0] $end
$var wire 32 . PC_4 [31:0] $end
$var wire 1 / PCSel $end
$var wire 1 0 MemRW $end
$var wire 32 1 Instr [31:0] $end
$var wire 3 2 ImmSel [2:0] $end
$var wire 32 3 DataR [31:0] $end
$var wire 1 4 BrUn $end
$var wire 1 5 BrLt $end
$var wire 1 6 BrEq $end
$var wire 1 7 BSel $end
$var wire 1 8 ASel $end
$var wire 4 9 ALUSel [3:0] $end
$scope module ALU_Top $end
$var wire 4 : control [3:0] $end
$var wire 32 ; alu_slt [31:0] $end
$var wire 32 < B [31:0] $end
$var wire 32 = ALU_result [31:0] $end
$var wire 32 > A [31:0] $end
$upscope $end
$scope module Controller $end
$var wire 11 ? red_inst [10:0] $end
$var wire 32 @ i_instuction [31:0] $end
$var wire 15 A control_word [14:0] $end
$var wire 2 B WBSel [1:0] $end
$var wire 1 + RegWEn $end
$var wire 1 / PCSel $end
$var wire 1 0 MemRW $end
$var wire 3 C ImmSel [2:0] $end
$var wire 1 4 BrUn $end
$var wire 1 5 BrLt $end
$var wire 1 6 BrEq $end
$var wire 1 7 BSel $end
$var wire 1 8 ASel $end
$var wire 4 D ALUSel [3:0] $end
$upscope $end
$scope module Data_mem $end
$var wire 32 E A_mem [31:0] $end
$var wire 1 0 MemRW $end
$var wire 1 ! clk $end
$var wire 32 F DataIP [31:0] $end
$var wire 32 G D_read [31:0] $end
$upscope $end
$scope module Imm_Gen $end
$var wire 3 H ImmSel [2:0] $end
$var wire 32 I immediate [31:0] $end
$var wire 32 J Instr [31:0] $end
$upscope $end
$scope module PCPlus4Top $end
$var wire 32 K PC_add [31:0] $end
$var wire 32 L PCP4_add [31:0] $end
$upscope $end
$scope module PC_Top $end
$var wire 1 ! clk $end
$var wire 1 " rst $end
$var wire 32 M PCP4 [31:0] $end
$var reg 32 N PC [31:0] $end
$upscope $end
$scope module branch_comp $end
$var wire 1 4 BrUn $end
$var wire 1 5 BrLt $end
$var wire 1 6 BrEq $end
$var wire 32 O B [31:0] $end
$var wire 32 P A [31:0] $end
$upscope $end
$scope module imem $end
$var wire 32 Q A [31:0] $end
$var wire 1 " rst $end
$var wire 32 R RD [31:0] $end
$upscope $end
$scope module mux3 $end
$var wire 32 S a [31:0] $end
$var wire 32 T b [31:0] $end
$var wire 32 U c [31:0] $end
$var wire 2 V sel [1:0] $end
$var wire 32 W d [31:0] $end
$upscope $end
$scope module muxA $end
$var wire 32 X b [31:0] $end
$var wire 1 8 sel $end
$var wire 32 Y c [31:0] $end
$var wire 32 Z a [31:0] $end
$upscope $end
$scope module muxB $end
$var wire 32 [ b [31:0] $end
$var wire 1 7 sel $end
$var wire 32 \ c [31:0] $end
$var wire 32 ] a [31:0] $end
$upscope $end
$scope module muxPC $end
$var wire 32 ^ a [31:0] $end
$var wire 32 _ b [31:0] $end
$var wire 1 / sel $end
$var wire 32 ` c [31:0] $end
$upscope $end
$scope module regfile $end
$var wire 5 a AddA [4:0] $end
$var wire 5 b AddB [4:0] $end
$var wire 5 c AddD [4:0] $end
$var wire 32 d DataD [31:0] $end
$var wire 1 + WE $end
$var wire 1 ! clk $end
$var wire 1 " rst $end
$var wire 32 e DataB [31:0] $end
$var wire 32 f DataA [31:0] $end
$var reg 5 g index [4:0] $end
$upscope $end
$upscope $end
$upscope $end
$enddefinitions $end
$comment Show the parameter values. $end
$dumpall
$end
#0
$dumpvars
b1 g
b0 f
b0 e
b0 d
b0 c
b0 b
b0 a
b100 `
b0 _
b100 ^
b0 ]
b0 \
b0 [
b0 Z
b0 Y
b0 X
b0 W
b1 V
b100 U
b0 T
b0 S
b0 R
b0 Q
b0 P
b0 O
b0 N
b100 M
b100 L
b0 K
b0 J
b0 I
b1 H
b0 G
b0 F
b0 E
b1010 D
b1 C
b1 B
b100110100101 A
b0 @
b10 ?
b0 >
b0 =
b0 <
b0 ;
b1010 :
b1010 9
08
17
16
05
04
b0 3
b1 2
b0 1
00
0/
b100 .
b100 -
b0 ,
1+
b1 *
b0 )
b0 (
b0 '
b0 &
b0 %
b0 $
b0 #
0"
1!
$end
#50
0!
#100
1!
#150
b0 9
b0 :
b0 D
b100100000101 A
b10010 ?
b101 c
b1010010011 1
b1010010011 @
b1010010011 J
b1010010011 R
0!
1"
#200
1/
b10 *
b10 B
b10 V
b1 2
b1 C
b1 H
17
b100100100000110 A
b1000 #
b1000 W
b1000 d
b10100 )
b10100 =
b10100 E
b10100 T
b10100 _
b1 ;
b10100 '
b10100 <
b10100 \
b10100 &
b10100 I
b10100 [
b1100110 ?
b10100 b
b101 a
b1 c
b1010000101000000011100111 1
b1010000101000000011100111 @
b1010000101000000011100111 J
b1010000101000000011100111 R
b10100 -
b10100 M
b10100 `
b1000 .
b1000 L
b1000 U
b1000 ^
b100 ,
b100 K
b100 N
b100 Q
b100 X
1!
#250
0!
#300
0/
b1 *
b1 B
b1 V
b100100000101 A
b11000 -
b11000 M
b11000 `
b101 )
b101 =
b101 E
b101 T
b101 _
b101 '
b101 <
b101 \
b101 &
b101 I
b101 [
b10010 ?
b101 b
b101 c
b101 #
b101 W
b101 d
b10100101000001010010011 1
b10100101000001010010011 @
b10100101000001010010011 J
b10100101000001010010011 R
b11000 .
b11000 L
b11000 U
b11000 ^
b10100 ,
b10100 K
b10100 N
b10100 Q
b10100 X
1!
#350
0!
#400
b110 '
b110 <
b110 \
b110 #
b110 W
b110 d
b110 &
b110 I
b110 [
b110 b
b110 a
b110 c
b110 )
b110 =
b110 E
b110 T
b110 _
b1 ;
b11000110000001100010011 1
b11000110000001100010011 @
b11000110000001100010011 J
b11000110000001100010011 R
b0 (
b0 >
b0 Y
b11100 -
b11100 M
b11100 `
b0 %
b0 P
b0 Z
b0 f
b0 $
b0 F
b0 O
b0 ]
b0 e
b11100 .
b11100 L
b11100 U
b11100 ^
b11000 ,
b11000 K
b11000 N
b11000 Q
b11000 X
1!
#450
0!
#500
1/
b10 *
b10 B
b10 V
b1 2
b1 C
b1 H
17
b100100100000110 A
b100000 #
b100000 W
b100000 d
b1000 '
b1000 <
b1000 \
b1000 &
b1000 I
b1000 [
b1000 )
b1000 =
b1000 E
b1000 T
b1000 _
b1 ;
b1100110 ?
b1000 b
b111 a
b10 c
b0 (
b0 >
b0 Y
b100000111000000101100111 1
b100000111000000101100111 @
b100000111000000101100111 J
b100000111000000101100111 R
b0 %
b0 P
b0 Z
b0 f
b0 $
b0 F
b0 O
b0 ]
b0 e
b1000 -
b1000 M
b1000 `
b100000 .
b100000 L
b100000 U
b100000 ^
b11100 ,
b11100 K
b11100 N
b11100 Q
b11100 X
1!
#550
0!
#600
0/
b1 *
b1 B
b1 V
b100100000101 A
15
b1100 -
b1100 M
b1100 `
06
b0 ;
b110 )
b110 =
b110 E
b110 T
b110 _
b1 '
b1 <
b1 \
b101 (
b101 >
b101 Y
b1 &
b1 I
b1 [
b1000 $
b1000 F
b1000 O
b1000 ]
b1000 e
b101 %
b101 P
b101 Z
b101 f
b10001 ?
b1 b
b101 a
b111 c
b110 #
b110 W
b110 d
b100101000001110010011 1
b100101000001110010011 @
b100101000001110010011 J
b100101000001110010011 R
b1100 .
b1100 L
b1100 U
b1100 ^
b1000 ,
b1000 K
b1000 N
b1000 Q
b1000 X
1!
#650
0!
#700
b111 #
b111 W
b111 d
b111 )
b111 =
b111 E
b111 T
b111 _
b110 (
b110 >
b110 Y
b110 %
b110 P
b110 Z
b110 f
b110 a
b1000 c
b100110000010000010011 1
b100110000010000010011 @
b100110000010000010011 J
b100110000010000010011 R
b10000 -
b10000 M
b10000 `
b10000 .
b10000 L
b10000 U
b10000 ^
b1100 ,
b1100 K
b1100 N
b1100 Q
b1100 X
1!
#750
0!
#800
1/
b10 *
b10 B
b10 V
b1 2
b1 C
b1 H
17
b100100100000110 A
b10100 #
b10100 W
b10100 d
05
b100010 )
b100010 =
b100010 E
b100010 T
b100010 _
b1 ;
b11100 '
b11100 <
b11100 \
b11100 &
b11100 I
b11100 [
b0 $
b0 F
b0 O
b0 ]
b0 e
b1100100 ?
b11100 b
b11 c
b1110000110000000111100111 1
b1110000110000000111100111 @
b1110000110000000111100111 J
b1110000110000000111100111 R
b100010 -
b100010 M
b100010 `
b10100 .
b10100 L
b10100 U
b10100 ^
b10000 ,
b10000 K
b10000 N
b10000 Q
b10000 X
1!
#850
0!
#900
0/
b1 *
b1 B
b1 V
b100100000101 A
b100110 -
b100110 M
b100110 `
16
b0 ;
b0 )
b0 =
b0 E
b0 T
b0 _
b0 '
b0 <
b0 \
b0 (
b0 >
b0 Y
b0 &
b0 I
b0 [
b0 %
b0 P
b0 Z
b0 f
b10010 ?
b0 b
b0 a
b0 c
b0 #
b0 W
b0 d
b10011 1
b10011 @
b10011 J
b10011 R
b100110 .
b100110 L
b100110 U
b100110 ^
b100010 ,
b100010 K
b100010 N
b100010 Q
b100010 X
1!
#950
0!
#1000
x4
x/
x8
x+
bx *
bx B
bx V
bx #
bx W
bx d
bx 3
bx G
bx S
x5
x6
bx 2
bx C
bx H
x7
bx 9
bx :
bx D
bx )
bx =
bx E
bx T
bx _
b0x ;
bx '
bx <
bx \
bx0xxx A
bx (
bx >
bx Y
bx &
bx I
bx [
bx $
bx F
bx O
bx ]
bx e
bx %
bx P
bx Z
bx f
bx ?
bx b
bx a
bx c
bx 1
bx @
bx J
bx R
bx -
bx M
bx `
b101010 .
b101010 L
b101010 U
b101010 ^
b100110 ,
b100110 K
b100110 N
b100110 Q
b100110 X
1!
#1050
0!
#1100
bx .
bx L
bx U
bx ^
bx ,
bx K
bx N
bx Q
bx X
1!
